{
	"format_version": "1.12.0",
	"minecraft:geometry": [
		{
			"description": {
				"identifier": "geometry.unknown",
				"texture_width": 64,
				"texture_height": 64,
				"visible_bounds_width": 8,
				"visible_bounds_height": 7,
				"visible_bounds_offset": [0, 2.5, 0]
			},
			"bones": [
				{
					"name": "main",
					"pivot": [0, 20, 0],
					"rotation": [12.5, 0, 0]
				},
				{
					"name": "sword",
					"parent": "main",
					"pivot": [0, 13.21374, 3.55626],
					"cubes": [
						{"origin": [-1, 10.90433, 2.5035], "size": [2, 7.5, 1], "inflate": -0.2, "pivot": [0, 11.33926, 3.57083], "rotation": [21.5, 0, 0], "uv": [40, 0]},
						{"origin": [-1, 15.15433, 3.1035], "size": [2, 1.25, 1.8], "inflate": -0.2, "pivot": [0, 11.33926, 3.57083], "rotation": [21.5, 0, 0], "uv": [6, 51]},
						{"origin": [-1, 12.35433, 3.1035], "size": [2, 1.25, 1.8], "inflate": -0.2, "pivot": [0, 11.33926, 3.57083], "rotation": [21.5, 0, 0], "uv": [51, 4]},
						{"origin": [-1, 7.05433, 3.5035], "size": [2, 1, 1.4], "inflate": -0.2, "pivot": [0, 11.33926, 3.57083], "rotation": [21.5, 0, 0], "uv": [6, 49]},
						{"origin": [-1, 5.15433, 3.5035], "size": [2, 1, 1.4], "inflate": -0.2, "pivot": [0, 11.33926, 3.57083], "rotation": [21.5, 0, 0], "uv": [48, 29]},
						{"origin": [-1, 9.97775, 3.5857], "size": [2, 1, 1.875], "inflate": -0.202, "pivot": [0, 11.33926, 3.57083], "rotation": [-1, 0, 0], "uv": [0, 51]},
						{"origin": [-1, 9.71217, 2.48904], "size": [2, 2, 1], "inflate": -0.202, "pivot": [0, 11.33926, 3.57083], "rotation": [47.75, 0, 0], "uv": [48, 26]},
						{"origin": [-1, 5.18793, 7.03515], "size": [2, 1.1, 1], "inflate": -0.202, "pivot": [0, 11.33926, 3.57083], "rotation": [-17.25, 0, 0], "uv": [48, 18]},
						{"origin": [-1, 3.50433, 2.9035], "size": [2, 7, 1], "inflate": -0.2, "pivot": [0, 11.33926, 3.57083], "rotation": [21.5, 0, 0], "uv": [24, 0]},
						{"origin": [-1, -0.09567, 4.5035], "size": [2, 18.5, 1], "inflate": -0.2, "pivot": [0, 11.33926, 3.57083], "rotation": [21.5, 0, 0], "uv": [0, 32]},
						{"origin": [-1, -0.13804, -0.56039], "size": [2, 1.125, 2.9], "inflate": -0.202, "pivot": [0, 11.33926, 3.57083], "rotation": [37.5, 0, 0], "uv": [46, 20]},
						{"origin": [-0.5, 24.37731, -4.28046], "size": [1, 17, 1.5], "inflate": -0.2, "pivot": [0, 32.17731, -3.78046], "rotation": [21.5, 0, 0], "uv": [32, 0]},
						{"origin": [-0.5, 19.77731, -5.58046], "size": [1, 5, 2.8], "inflate": -0.2, "pivot": [0, 32.17731, -3.78046], "rotation": [21.5, 0, 0], "uv": [42, 15]},
						{"origin": [-1, 18.67914, 0.67574], "size": [2, 1, 1], "inflate": -0.19, "pivot": [0, 20.07914, -2.02426], "rotation": [54, 0, 0], "uv": [52, 2]},
						{"origin": [-1, 16.92914, 0.82574], "size": [2, 1, 1], "inflate": -0.19, "pivot": [0, 18.32914, -1.87426], "rotation": [54, 0, 0], "uv": [52, 2]},
						{"origin": [-1, 14.92914, 0.52574], "size": [2, 1, 1], "inflate": -0.19, "pivot": [0, 16.32914, -2.17426], "rotation": [54, 0, 0], "uv": [52, 2]},
						{"origin": [-1, 0.72914, 6.27574], "size": [2, 1, 1], "inflate": -0.19, "pivot": [0, 2.12914, 3.57574], "rotation": [54, 0, 0], "uv": [52, 2]},
						{"origin": [-1, 1.12914, 7.47574], "size": [2, 1, 1], "inflate": -0.19, "pivot": [0, 2.52914, 4.77574], "rotation": [54, 0, 0], "uv": [52, 2]},
						{"origin": [-1, -1.87086, 7.47574], "size": [2, 1, 1], "inflate": -0.19, "pivot": [0, -0.47086, 4.77574], "rotation": [54, 0, 0], "uv": [52, 2]},
						{"origin": [-0.5, 19.87914, -0.32426], "size": [1, 1, 1], "inflate": -0.19, "pivot": [0, 20.07914, -2.02426], "rotation": [54, 0, 0], "uv": [53, 2]},
						{"origin": [-0.5, 19.17914, -4.62426], "size": [1, 1, 4.5], "inflate": -0.202, "pivot": [0, 20.07914, -2.02426], "rotation": [54, 0, 0], "uv": [32, 16]},
						{"origin": [-1, 17.77199, -0.11059], "size": [2, 4, 1.075], "inflate": -0.2, "pivot": [0, 21.59699, 0.98941], "rotation": [21.5, 0, 0], "uv": [13, 48]},
						{"origin": [-1, 21.37199, -0.11059], "size": [2, 1.6, 1.075], "inflate": -0.2, "pivot": [0, 21.59699, 0.98941], "rotation": [21.5, 0, 0], "uv": [40, 22]},
						{"origin": [-1, 21.37199, -0.78559], "size": [2, 1, 1.075], "inflate": -0.2, "pivot": [0, 21.59699, 0.98941], "rotation": [21.5, 0, 0], "uv": [0, 6]},
						{"origin": [-1, 17.77199, -0.78559], "size": [2, 4, 1.075], "inflate": -0.2, "pivot": [0, 21.59699, 0.98941], "rotation": [21.5, 0, 0], "uv": [46, 5]},
						{"origin": [-1, 17.77199, -1.43559], "size": [2, 4, 1.05], "inflate": -0.2, "pivot": [0, 21.59699, 0.98941], "rotation": [21.5, 0, 0], "uv": [46, 0]},
						{"origin": [-1, 19.55478, -0.1447], "size": [2, 4, 1], "inflate": -0.202, "pivot": [0, 23.35478, 0.0553], "rotation": [-24, 0, 0], "uv": [46, 10]},
						{"origin": [-1, 18.00433, 4.5035], "size": [2, 6, 1], "inflate": -0.2, "pivot": [0, 11.33926, 3.57083], "rotation": [21.5, 0, 0], "uv": [40, 8]},
						{"origin": [-1, 18.17561, 5.38801], "size": [2, 2.5, 1.5], "inflate": -0.202, "pivot": [0, 11.33926, 3.57083], "rotation": [44, 0, 0], "uv": [48, 15]},
						{"origin": [-1, 19.67883, 5.28897], "size": [2, 1.5, 2.5], "inflate": -0.204, "pivot": [0, 11.33926, 3.57083], "rotation": [46.5, 0, 0], "uv": [32, 21]},
						{"origin": [-0.5, 23.21974, -2.68372], "size": [1, 1.5, 2.8], "inflate": -0.202, "pivot": [0, 24.51974, -2.48372], "rotation": [71.5, 0, 0], "uv": [48, 23]},
						{"origin": [-0.5, 40.24112, -7.5581], "size": [1, 15, 1.5], "inflate": -0.2, "pivot": [0, 40.44112, -7.3581], "rotation": [19, 0, 0], "uv": [36, 0]},
						{"origin": [-0.5, 54.04569, -12.31139], "size": [1, 15, 1.5], "inflate": -0.2, "pivot": [0, 54.24569, -12.11139], "rotation": [16.5, 0, 0], "uv": [18, 32]},
						{"origin": [-0.5, 68.04446, -16.45801], "size": [1, 2, 1], "inflate": -0.2, "pivot": [0, 68.24446, -16.25801], "rotation": [-11, 0, 0], "uv": [19, 51]},
						{"origin": [-0.5, 67.90058, -16.16374], "size": [1, 2, 1], "inflate": -0.2, "pivot": [0, 69.70058, -15.36374], "rotation": [8.5, 0, 0], "uv": [19, 48]},
						{"origin": [-1, -0.09567, 2.5035], "size": [2, 4.7, 2.45], "inflate": -0.2, "pivot": [0, 11.33926, 3.57083], "rotation": [21.5, 0, 0], "uv": [0, 0]}
					]
				},
				{
					"name": "blade",
					"parent": "sword",
					"pivot": [0.001, 24.59304, -2.29763],
					"cubes": [
						{
							"origin": [-0.201, 55.53358, -13.18599],
							"size": [0.402, 14, 1.2],
							"inflate": -0.2,
							"pivot": [0.001, 55.73358, -13.78599],
							"rotation": [16.5, 0, 0],
							"uv": {
								"north": {"uv": [16, 32], "uv_size": [0, 0]},
								"east": {"uv": [14, 32], "uv_size": [1, 14]},
								"south": {"uv": [18, 32], "uv_size": [0, 0]},
								"west": {"uv": [17, 32], "uv_size": [1, 14]},
								"up": {"uv": [16, 32], "uv_size": [0, 0]},
								"down": {"uv": [16, 32], "uv_size": [0, 0]}
							}
						},
						{
							"origin": [-0.201, 39.83797, -7.78156],
							"size": [0.402, 17, 1.2],
							"inflate": -0.2,
							"pivot": [0.001, 40.03797, -8.38156],
							"rotation": [19, 0, 0],
							"uv": {
								"north": {"uv": [8, 32], "uv_size": [0, 0]},
								"east": {"uv": [6, 32], "uv_size": [1, 17]},
								"south": {"uv": [10, 32], "uv_size": [0, 0]},
								"west": {"uv": [9, 32], "uv_size": [1, 17]},
								"up": {"uv": [8, 32], "uv_size": [0, 0]},
								"down": {"uv": [8, 32], "uv_size": [0, 0]}
							}
						},
						{
							"origin": [-0.201, 24.39304, -1.69763],
							"size": [0.402, 17, 1.2],
							"inflate": -0.2,
							"pivot": [0.001, 24.59304, -2.29763],
							"rotation": [21.5, 0, 0],
							"uv": {
								"north": {"uv": [12, 32], "uv_size": [0, 0]},
								"east": {"uv": [10, 32], "uv_size": [1, 17]},
								"south": {"uv": [14, 32], "uv_size": [0, 0]},
								"west": {"uv": [13, 32], "uv_size": [1, 17]},
								"up": {"uv": [13, 34], "uv_size": [0, 0]},
								"down": {"uv": [13, 32], "uv_size": [0, 0]}
							}
						},
						{
							"origin": [-0.201, 24.59304, -2.49763],
							"size": [0.402, 2.2, 1.2],
							"inflate": -0.2,
							"pivot": [0.001, 24.59304, -2.29763],
							"rotation": [21.5, 0, 0],
							"uv": {
								"north": {"uv": [12, 32], "uv_size": [0, 0]},
								"east": {"uv": [11, 47], "uv_size": [1, 2]},
								"south": {"uv": [14, 32], "uv_size": [0, 0]},
								"west": {"uv": [12, 47], "uv_size": [1, 2]},
								"up": {"uv": [13, 34], "uv_size": [0, 0]},
								"down": {"uv": [13, 32], "uv_size": [0, 0]}
							}
						}
					]
				},
				{
					"name": "bladeGlow",
					"parent": "sword",
					"pivot": [0.001, 24.59304, -2.29763],
					"cubes": [
						{
							"origin": [-0.201, 68.57353, -17.8486],
							"size": [0.402, 4, 2],
							"inflate": -0.2,
							"pivot": [0.001, 68.77353, -17.6486],
							"rotation": [-3.5, 0, 0],
							"uv": {
								"north": {"uv": [40, 17], "uv_size": [0, 0]},
								"east": {"uv": [38, 16], "uv_size": [2, 4]},
								"south": {"uv": [40, 17], "uv_size": [0, 0]},
								"west": {"uv": [40, 16], "uv_size": [2, 4]},
								"up": {"uv": [40, 17], "uv_size": [0, 0]},
								"down": {"uv": [40, 17], "uv_size": [0, 0]}
							}
						},
						{
							"origin": [-0.201, 55.53358, -13.98599],
							"size": [0.402, 14, 1.2],
							"inflate": -0.2,
							"pivot": [0.001, 55.73358, -13.78599],
							"rotation": [16.5, 0, 0],
							"uv": {
								"north": {"uv": [16, 32], "uv_size": [0, 0]},
								"east": {"uv": [15, 32], "uv_size": [1, 14]},
								"south": {"uv": [18, 32], "uv_size": [0, 0]},
								"west": {"uv": [16, 32], "uv_size": [1, 14]},
								"up": {"uv": [16, 32], "uv_size": [0, 0]},
								"down": {"uv": [16, 32], "uv_size": [0, 0]}
							}
						},
						{
							"origin": [-0.201, 39.83797, -8.58156],
							"size": [0.402, 17, 1.2],
							"inflate": -0.2,
							"pivot": [0.001, 40.03797, -8.38156],
							"rotation": [19, 0, 0],
							"uv": {
								"north": {"uv": [8, 32], "uv_size": [0, 0]},
								"east": {"uv": [7, 32], "uv_size": [1, 17]},
								"south": {"uv": [10, 32], "uv_size": [0, 0]},
								"west": {"uv": [8, 32], "uv_size": [1, 17]},
								"up": {"uv": [8, 32], "uv_size": [0, 0]},
								"down": {"uv": [8, 32], "uv_size": [0, 0]}
							}
						},
						{
							"origin": [-0.201, 26.39304, -2.49763],
							"size": [0.402, 15, 1.2],
							"inflate": -0.2,
							"pivot": [0.001, 24.59304, -2.29763],
							"rotation": [21.5, 0, 0],
							"uv": {
								"north": {"uv": [12, 32], "uv_size": [0, 0]},
								"east": {"uv": [11, 32], "uv_size": [1, 15]},
								"south": {"uv": [14, 32], "uv_size": [0, 0]},
								"west": {"uv": [12, 32], "uv_size": [1, 15]},
								"up": {"uv": [13, 34], "uv_size": [0, 0]},
								"down": {"uv": [13, 32], "uv_size": [0, 0]}
							}
						}
					]
				},
				{
					"name": "rightarm",
					"parent": "main",
					"pivot": [-4.3, 8.8, 21.8],
					"rotation": [-101.81106, -12.40003, -2.46982],
					"cubes": [
						{"origin": [-8.3, -15.2, 17.8], "size": [8, 24, 8], "uv": [24, 24]}
					]
				},
				{
					"name": "leftarm",
					"pivot": [22.7, 4.3, 12.4],
					"rotation": [-51.17547, 69.31123, 48.39778],
					"cubes": [
						{"origin": [18.7, -19.7, 8.4], "size": [8, 24, 8], "uv": [0, 0]}
					]
				},
				{
					"name": "_camera_",
					"pivot": [14.3, 28.15, 31.5]
				}
			]
		}
	]
}